odoo8_addon_website_crm_privacy_policy-8.0.1.0.0.99.dev13-py3.8-nspkg.pth
odoo_addons/website_crm_privacy_policy/README.rst
odoo_addons/website_crm_privacy_policy/__init__.py
odoo_addons/website_crm_privacy_policy/__openerp__.py
odoo_addons/website_crm_privacy_policy/i18n/ca.po
odoo_addons/website_crm_privacy_policy/i18n/de.po
odoo_addons/website_crm_privacy_policy/i18n/el_GR.po
odoo_addons/website_crm_privacy_policy/i18n/es.po
odoo_addons/website_crm_privacy_policy/i18n/fr.po
odoo_addons/website_crm_privacy_policy/i18n/it.po
odoo_addons/website_crm_privacy_policy/i18n/pt_BR.po
odoo_addons/website_crm_privacy_policy/i18n/ru.po
odoo_addons/website_crm_privacy_policy/i18n/sl.po
odoo_addons/website_crm_privacy_policy/i18n/website_crm_privacy_policy.pot
odoo_addons/website_crm_privacy_policy/static/description/icon.png
odoo_addons/website_crm_privacy_policy/static/src/js/scripts.js
odoo_addons/website_crm_privacy_policy/views/assets.xml
odoo_addons/website_crm_privacy_policy/views/templates.xml
odoo8_addon_website_crm_privacy_policy-8.0.1.0.0.99.dev13.dist-info/METADATA
odoo8_addon_website_crm_privacy_policy-8.0.1.0.0.99.dev13.dist-info/WHEEL
odoo8_addon_website_crm_privacy_policy-8.0.1.0.0.99.dev13.dist-info/namespace_packages.txt
odoo8_addon_website_crm_privacy_policy-8.0.1.0.0.99.dev13.dist-info/top_level.txt
odoo8_addon_website_crm_privacy_policy-8.0.1.0.0.99.dev13.dist-info/RECORD
